golfity/__init__.py
golfity/__main__.py
golfity/arrays.py
golfity-0.0.9.dist-info/METADATA
golfity-0.0.9.dist-info/WHEEL
golfity-0.0.9.dist-info/entry_points.txt
golfity-0.0.9.dist-info/top_level.txt
golfity-0.0.9.dist-info/RECORD
