Metadata-Version: 2.1
Name: golfity
Version: 0.0.9
Home-page: https://github.com/cole-wilson/parity
Author: Cole Wilson
Author-email: cole@colewilson.xyz
License: none
Classifier: Programming Language :: Python :: 3
Requires-Python: >=3.6
Requires-Dist: typing
Requires-Dist: adicity
